scigeo/__init__.py
scigeo/climate.py
scigeo/geobox.py
scigeo/geoface.py
scigeo/meteo.py
scigeo/remotesensing.py
scigeo-0.0.15.dist-info/METADATA
scigeo-0.0.15.dist-info/WHEEL
scigeo-0.0.15.dist-info/top_level.txt
scigeo-0.0.15.dist-info/RECORD
